sphinx_needs_enterprise/__init__.py
sphinx_needs_enterprise/config.py
sphinx_needs_enterprise/exceptions.py
sphinx_needs_enterprise/extensions/__init__.py
sphinx_needs_enterprise/extensions/extension.py
sphinx_needs_enterprise/license.py
sphinx_needs_enterprise/scripts/__init__.py
sphinx_needs_enterprise/scripts/cli.py
sphinx_needs_enterprise/scripts/loader.py
sphinx_needs_enterprise/scripts/utils.py
sphinx_needs_enterprise/services/__init__.py
sphinx_needs_enterprise/services/azure.py
sphinx_needs_enterprise/services/codebeamer.py
sphinx_needs_enterprise/services/elasticsearch.py
sphinx_needs_enterprise/services/excel.py
sphinx_needs_enterprise/services/jira.py
sphinx_needs_enterprise/sne.py
sphinx_needs_enterprise/templates/needs.rst.template
sphinx_needs_enterprise/util.py
sphinx_needs_enterprise/version.py
sphinx_needs_enterprise-1.0.1.dist-info/LICENSE
sphinx_needs_enterprise-1.0.1.dist-info/METADATA
sphinx_needs_enterprise-1.0.1.dist-info/WHEEL
sphinx_needs_enterprise-1.0.1.dist-info/entry_points.txt
sphinx_needs_enterprise-1.0.1.dist-info/RECORD
