Metadata-Version: 2.1
Name: sphinx-needs-enterprise
Version: 1.0.1
Summary: 
Home-page: http://github.com/useblocks/sphinx-needs-enterprise
License: BSL 1.1
Author: team useblocks
Requires-Python: >3.7,<4.0
Classifier: License :: Other/Proprietary License
Classifier: Programming Language :: Python :: 3
Classifier: Programming Language :: Python :: 3.8
Classifier: Programming Language :: Python :: 3.9
Classifier: Programming Language :: Python :: 3.10
Classifier: Programming Language :: Python :: 3.11
Provides-Extra: docs
Requires-Dist: azure-devops (>=6.0.0-beta.4)
Requires-Dist: click (>=7.0)
Requires-Dist: elasticsearch (>=7.15)
Requires-Dist: jinja2 (>=2)
Requires-Dist: jira2markdown (>=0.1)
Requires-Dist: licensing (>=0.31)
Requires-Dist: m2r2 (>=0.2)
Requires-Dist: openpyxl (>=3.0.0)
Requires-Dist: requests (>=2)
Requires-Dist: sphinx (>=4.2)
Requires-Dist: sphinx-needs (>=1.0.1)
Requires-Dist: sphinxcontrib-programoutput (>=0.17)
Requires-Dist: tqdm (>=4.40)
Project-URL: Documentation, https://useblocks.com/sphinx-needs-enterprise
Project-URL: Repository, http://github.com/useblocks/sphinx-needs-enterprise
